seqparser/__init__.py
seqparser/__main__.py
seqparser/regIndex.txt
seqparser/seqparser.py
seqparser-1.1.2.dist-info/METADATA
seqparser-1.1.2.dist-info/WHEEL
seqparser-1.1.2.dist-info/entry_points.txt
seqparser-1.1.2.dist-info/top_level.txt
seqparser-1.1.2.dist-info/RECORD
