Metadata-Version: 2.1
Name: seqparser
Version: 1.1.2
Summary: Cli tool to find specific regular expression like email, ip adress, phone number, bitcoin adress ... in a file
Home-page: https://github.com/remiflavien1/seqparser
Author: shadawck
Author-email: hug211mire@gmail.com
License: MIT
Keywords: security,parser,forensic,analysis,sequence parser,regex
Platform: UNKNOWN
Classifier: License :: OSI Approved :: MIT License
Classifier: Programming Language :: Python :: 3
Classifier: Programming Language :: Python :: 3.7
Classifier: Topic :: Security
Classifier: Topic :: Scientific/Engineering :: Information Analysis
Classifier: Topic :: Internet :: Log Analysis
Requires-Dist: docopt
Provides-Extra: test
Requires-Dist: pytest ; extra == 'test'
Requires-Dist: pytest-cov ; extra == 'test'
